{
  "_class": "symbolInstance",
  "booleanOperation": 0,
  "clippingMaskMode": 0,
  "do_objectID": "10D4B388-08C2-41A4-81B7-2F1E7385629C",
  "exportOptions": {
    "_class": "exportOptions",
    "do_objectID": "3C6F86DF-4D60-422E-8FC3-9947A009CE35",
    "exportFormats": [
    ],
    "includedLayerIds": [
    ],
    "layerOptions": 0,
    "shouldTrim": false
  },
  "frame": {
    "_class": "rect",
    "constrainProportions": false,
    "do_objectID": "DA70FED0-7C0C-4F89-BA55-FD2E1D9CF0B0",
    "height": 96,
    "width": 285,
    "x": 0,
    "y": 94
  },
  "hasClippingMask": false,
  "horizontalSpacing": 0,
  "isFixedToViewport": false,
  "isFlippedHorizontal": false,
  "isFlippedVertical": false,
  "isLocked": false,
  "isVisible": true,
  "layerListExpandedType": 0,
  "name": "1: Atoms / Buttons / Primary / Text / Default Copy 16",
  "nameIsFixed": false,
  "originalObjectID": "7C1637A1-0321-4C69-8D89-C45372E7A136",
  "overrideValues": [
    {
      "_class": "overrideValue",
      "do_objectID": "1E9185D1-BF42-46EE-A795-E7B4C0FB4010",
      "overrideName": "B1AE6CF3-092E-44AB-AA90-E2B43212F8CE_stringValue",
      "value": " "
    }
  ],
  "resizingConstraint": 63,
  "resizingType": 0,
  "rotation": 0,
  "scale": 1,
  "shouldBreakMaskChain": false,
  "style": {
    "_class": "style",
    "do_objectID": "27D8A46C-52F9-4909-AF90-473F1E2F9193",
    "endMarkerType": 0,
    "miterLimit": 10,
    "startMarkerType": 0,
    "windingRule": 1
  },
  "symbolID": "D1BC1A1A-8E61-43AB-A29C-371F41057450",
  "verticalSpacing": 0
}