{
  "_class": "symbolInstance",
  "booleanOperation": 0,
  "clippingMaskMode": 0,
  "do_objectID": "A3885219-17A3-4B93-AFAF-7BE7402C102C",
  "exportOptions": {
    "_class": "exportOptions",
    "do_objectID": "704764F0-437C-484E-B090-25682AD0B4B7",
    "exportFormats": [
    ],
    "includedLayerIds": [
    ],
    "layerOptions": 0,
    "shouldTrim": false
  },
  "frame": {
    "_class": "rect",
    "constrainProportions": false,
    "do_objectID": "C7B5128C-70EF-4780-8E7B-83BC27821483",
    "height": 24,
    "width": 24,
    "x": 0,
    "y": 0
  },
  "hasClippingMask": false,
  "horizontalSpacing": 0,
  "isFixedToViewport": false,
  "isFlippedHorizontal": false,
  "isFlippedVertical": false,
  "isLocked": false,
  "isVisible": true,
  "layerListExpandedType": 0,
  "name": "↳Color",
  "nameIsFixed": true,
  "originalObjectID": "ABC9242C-1FB2-495B-BF29-3B7BEC76DD6C",
  "overrideValues": [
  ],
  "resizingConstraint": 63,
  "resizingType": 0,
  "rotation": 0,
  "scale": 1,
  "shouldBreakMaskChain": false,
  "style": {
    "_class": "style",
    "do_objectID": "F7B1F14C-22CD-49D2-BD8F-0FF81B47D81A",
    "endMarkerType": 0,
    "miterLimit": 10,
    "startMarkerType": 0,
    "windingRule": 1
  },
  "symbolID": "94BCDD5C-1692-4C47-BFDE-3FDBD81D2E06",
  "userInfo": {
    "com.animaapp.stc-sketch-plugin": {
      "kModelPropertiesKey": {
      }
    }
  },
  "verticalSpacing": 0
}