{
  "_class": "symbolInstance",
  "booleanOperation": 0,
  "clippingMaskMode": 0,
  "do_objectID": "7343994C-D365-4B8C-AC7D-D852022FE666",
  "exportOptions": {
    "_class": "exportOptions",
    "do_objectID": "92CAC9A1-1DFA-4D7F-ABA2-4362B10CD79A",
    "exportFormats": [
      {
        "_class": "exportFormat",
        "absoluteSize": 0,
        "fileFormat": "svg",
        "name": "",
        "namingScheme": 0,
        "scale": 1,
        "visibleScaleType": 0
      }
    ],
    "includedLayerIds": [
    ],
    "layerOptions": 0,
    "shouldTrim": false
  },
  "frame": {
    "_class": "rect",
    "constrainProportions": false,
    "do_objectID": "1E8BEEC5-8A31-4AC0-AD0F-EBD0C958290D",
    "height": 18,
    "width": 18,
    "x": 256,
    "y": 35
  },
  "hasClippingMask": false,
  "horizontalSpacing": 0,
  "isFixedToViewport": false,
  "isFlippedHorizontal": false,
  "isFlippedVertical": false,
  "isLocked": false,
  "isVisible": true,
  "layerListExpandedType": 0,
  "name": "Icon:",
  "nameIsFixed": true,
  "originalObjectID": "DBF377BA-C5C4-42FE-81A8-3A4FC4F4CA9B",
  "overrideValues": [
    {
      "_class": "overrideValue",
      "do_objectID": "A59A8619-C9EC-4333-B6C4-A4D21956EFD0",
      "overrideName": "7F64276D-0D4B-4DDB-BD71-CE978D61794E_symbolID",
      "value": "465CA714-EB61-4FAC-BB89-47FCCD12C27D"
    }
  ],
  "resizingConstraint": 12,
  "resizingType": 0,
  "rotation": 0,
  "scale": 0.75,
  "shouldBreakMaskChain": false,
  "style": {
    "_class": "style",
    "blur": {
      "_class": "blur",
      "center": "{0.5, 0.5}",
      "do_objectID": "79BF2F72-6464-4298-9582-3A451093BB4D",
      "isEnabled": false,
      "motionAngle": 0,
      "radius": 7.5,
      "saturation": 1,
      "type": 0
    },
    "do_objectID": "4F09B720-DDC2-4A8F-BDF3-514306020057",
    "endMarkerType": 0,
    "miterLimit": 10,
    "startMarkerType": 0,
    "windingRule": 1
  },
  "symbolID": "91C08588-68B6-48B7-9B3A-E02CC71F9EB1",
  "verticalSpacing": 0
}