{
  "_class": "symbolInstance",
  "booleanOperation": 0,
  "clippingMaskMode": 0,
  "do_objectID": "39BF7F6E-3180-4D28-B351-70B5848E8CA6",
  "exportOptions": {
    "_class": "exportOptions",
    "do_objectID": "26FF1422-7914-4435-8901-68272D894191",
    "exportFormats": [
      {
        "_class": "exportFormat",
        "absoluteSize": 0,
        "fileFormat": "svg",
        "name": "",
        "namingScheme": 0,
        "scale": 1,
        "visibleScaleType": 0
      }
    ],
    "includedLayerIds": [
    ],
    "layerOptions": 0,
    "shouldTrim": false
  },
  "frame": {
    "_class": "rect",
    "constrainProportions": true,
    "do_objectID": "4A9B2131-FAC1-4C41-8219-19F341ADBC28",
    "height": 18,
    "width": 18,
    "x": 11,
    "y": 11
  },
  "hasClippingMask": false,
  "horizontalSpacing": 0,
  "isFixedToViewport": false,
  "isFlippedHorizontal": false,
  "isFlippedVertical": false,
  "isLocked": false,
  "isVisible": true,
  "layerListExpandedType": 0,
  "name": "Right:",
  "nameIsFixed": true,
  "originalObjectID": "FFA34B71-617B-420A-B6D0-667B73C1B9F9",
  "overrideValues": [
    {
      "_class": "overrideValue",
      "do_objectID": "04403660-C739-47CC-A2F6-CB3BAFFE648A",
      "overrideName": "A886A604-D096-4996-A397-BA05153753D4_symbolID",
      "value": "61BCA14B-D3E3-4E0D-9FA6-BAE1EF824694"
    }
  ],
  "resizingConstraint": 45,
  "resizingType": 0,
  "rotation": 0,
  "scale": 1,
  "shouldBreakMaskChain": false,
  "style": {
    "_class": "style",
    "do_objectID": "354D763C-8F91-4FFB-890A-7F83B03E0DEC",
    "endMarkerType": 0,
    "miterLimit": 10,
    "startMarkerType": 0,
    "windingRule": 1
  },
  "symbolID": "DAF622D6-5797-4C60-BD6C-ADAD17985F95",
  "verticalSpacing": 0
}