{
  "_class": "text",
  "attributedString": {
    "_class": "attributedString",
    "attributes": [
      {
        "_class": "stringAttribute",
        "attributes": {
          "MSAttributedStringColorAttribute": {
            "_class": "color",
            "alpha": 0.87,
            "blue": 0,
            "green": 0,
            "red": 0
          },
          "MSAttributedStringFontAttribute": {
            "_class": "fontDescriptor",
            "attributes": {
              "name": "OpenSans",
              "size": 14
            }
          },
          "kerning": 0.246536,
          "ligature": 0,
          "paragraphStyle": {
            "_class": "paragraphStyle",
            "alignment": 0,
            "allowsDefaultTighteningForTruncation": 0,
            "maximumLineHeight": 24,
            "minimumLineHeight": 24
          }
        },
        "length": 7,
        "location": 0
      }
    ],
    "string": "Enabled"
  },
  "automaticallyDrawOnUnderlyingPath": false,
  "booleanOperation": 0,
  "clippingMaskMode": 0,
  "do_objectID": "69BDBCB7-9558-4AC4-9A57-A498726EC8ED",
  "dontSynchroniseWithSymbol": false,
  "exportOptions": {
    "_class": "exportOptions",
    "do_objectID": "3C79FF28-2CA3-4B4A-A6EB-B5E5B831E286",
    "exportFormats": [
    ],
    "includedLayerIds": [
    ],
    "layerOptions": 0,
    "shouldTrim": false
  },
  "frame": {
    "_class": "rect",
    "constrainProportions": false,
    "do_objectID": "C35216FD-074F-454E-BF93-1E46D796AB35",
    "height": 24,
    "width": 55,
    "x": 0,
    "y": 0
  },
  "glyphBounds": "{{1, 6}, {52, 12}}",
  "hasClippingMask": false,
  "isFixedToViewport": false,
  "isFlippedHorizontal": false,
  "isFlippedVertical": false,
  "isLocked": false,
  "isVisible": true,
  "layerListExpandedType": 0,
  "lineSpacingBehaviour": 2,
  "name": "Input:",
  "nameIsFixed": true,
  "resizingConstraint": 42,
  "resizingType": 0,
  "rotation": 0,
  "shouldBreakMaskChain": false,
  "style": {
    "_class": "style",
    "do_objectID": "DED020B7-5688-4516-8BF8-CBF44C44F1AA",
    "endMarkerType": 0,
    "miterLimit": 10,
    "startMarkerType": 0,
    "textStyle": {
      "_class": "textStyle",
      "do_objectID": "7D478337-A8D1-463F-B0BE-B4123E940B62",
      "encodedAttributes": {
        "MSAttributedStringColorAttribute": {
          "_class": "color",
          "alpha": 0.87,
          "blue": 0,
          "green": 0,
          "red": 0
        },
        "MSAttributedStringFontAttribute": {
          "_class": "fontDescriptor",
          "attributes": {
            "name": "OpenSans",
            "size": 14
          }
        },
        "kerning": 0.246536,
        "ligature": 0,
        "paragraphStyle": {
          "_class": "paragraphStyle",
          "alignment": 0,
          "allowsDefaultTighteningForTruncation": 0,
          "maximumLineHeight": 24,
          "minimumLineHeight": 24
        }
      },
      "verticalAlignment": 0
    },
    "windingRule": 1
  },
  "textBehaviour": 0
}