{
  "_class": "rectangle",
  "booleanOperation": -1,
  "clippingMaskMode": 0,
  "do_objectID": "06FF6BA0-BE6B-46D8-8C36-B977AD2F6200",
  "edited": false,
  "exportOptions": {
    "_class": "exportOptions",
    "do_objectID": "C3F7A62F-21F0-4DA1-A951-E9FD45CDE586",
    "exportFormats": [
    ],
    "includedLayerIds": [
    ],
    "layerOptions": 0,
    "shouldTrim": false
  },
  "fixedRadius": 0,
  "frame": {
    "_class": "rect",
    "constrainProportions": false,
    "do_objectID": "6C7D1141-5E5D-4382-B16F-64B9DDEE3CCC",
    "height": 47.5,
    "width": 285,
    "x": 0,
    "y": 47.5
  },
  "hasClippingMask": false,
  "hasConvertedToNewRoundCorners": true,
  "isClosed": true,
  "isFixedToViewport": false,
  "isFlippedHorizontal": false,
  "isFlippedVertical": false,
  "isLocked": false,
  "isVisible": true,
  "layerListExpandedType": 1,
  "name": "Rectangle 2 Copy 2",
  "nameIsFixed": false,
  "pointRadiusBehaviour": 1,
  "points": [
    {
      "_class": "curvePoint",
      "cornerRadius": 0,
      "curveFrom": "{0, 0}",
      "curveMode": 1,
      "curveTo": "{0, 0}",
      "hasCurveFrom": false,
      "hasCurveTo": false,
      "point": "{0, 0}"
    },
    {
      "_class": "curvePoint",
      "cornerRadius": 0,
      "curveFrom": "{1.0000000000000047, 0}",
      "curveMode": 1,
      "curveTo": "{1.0000000000000047, 0}",
      "hasCurveFrom": false,
      "hasCurveTo": false,
      "point": "{1.0000000000000047, 0}"
    },
    {
      "_class": "curvePoint",
      "cornerRadius": 0,
      "curveFrom": "{1.0000000000000047, 0.99999999999999989}",
      "curveMode": 1,
      "curveTo": "{1.0000000000000047, 0.99999999999999989}",
      "hasCurveFrom": false,
      "hasCurveTo": false,
      "point": "{1.0000000000000047, 0.99999999999999989}"
    },
    {
      "_class": "curvePoint",
      "cornerRadius": 0,
      "curveFrom": "{0, 0.99999999999999989}",
      "curveMode": 1,
      "curveTo": "{0, 0.99999999999999989}",
      "hasCurveFrom": false,
      "hasCurveTo": false,
      "point": "{0, 0.99999999999999989}"
    }
  ],
  "resizingConstraint": 63,
  "resizingType": 0,
  "rotation": 0,
  "sharedStyleID": "B88732DA-1DC6-418D-9451-4DD3416832AF",
  "shouldBreakMaskChain": false,
  "style": {
    "_class": "style",
    "blur": {
      "_class": "blur",
      "center": "{0.5, 0.5}",
      "do_objectID": "7FBBFE42-3038-42DD-9E4A-27DBE12FF5A5",
      "isEnabled": false,
      "motionAngle": 0,
      "radius": 15.83333333333333,
      "saturation": 1,
      "type": 0
    },
    "do_objectID": "261E94DC-FA3A-4D20-8913-80F76470E460",
    "endMarkerType": 0,
    "fills": [
      {
        "_class": "fill",
        "color": {
          "_class": "color",
          "alpha": 1,
          "blue": 0.8627450980392157,
          "green": 0.6392156862745099,
          "red": 0.5372549019607843
        },
        "fillType": 0,
        "isEnabled": true,
        "noiseIndex": 0,
        "noiseIntensity": 0,
        "patternFillType": 0,
        "patternTileScale": 1
      }
    ],
    "miterLimit": 10,
    "startMarkerType": 0,
    "windingRule": 1
  }
}