{
  "_class": "text",
  "attributedString": {
    "_class": "attributedString",
    "attributes": [
      {
        "_class": "stringAttribute",
        "attributes": {
          "MSAttributedStringColorAttribute": {
            "_class": "color",
            "alpha": 1,
            "blue": 0.2941176470588236,
            "green": 0.2941176470588236,
            "red": 1
          },
          "MSAttributedStringFontAttribute": {
            "_class": "fontDescriptor",
            "attributes": {
              "name": "OpenSans",
              "size": 14
            }
          },
          "kerning": 0,
          "paragraphStyle": {
            "_class": "paragraphStyle",
            "alignment": 0,
            "baseWritingDirection": 0,
            "headerLevel": 1,
            "maximumLineHeight": 24,
            "minimumLineHeight": 24
          }
        },
        "length": 11,
        "location": 0
      }
    ],
    "string": "Wrong value"
  },
  "automaticallyDrawOnUnderlyingPath": false,
  "booleanOperation": 0,
  "clippingMaskMode": 0,
  "do_objectID": "CD4A55E3-777B-4EF4-88BE-D611F24B7ED5",
  "dontSynchroniseWithSymbol": true,
  "exportOptions": {
    "_class": "exportOptions",
    "do_objectID": "3940F1A7-B219-47C3-89C9-2302B5A7B1D5",
    "exportFormats": [
    ],
    "includedLayerIds": [
    ],
    "layerOptions": 0,
    "shouldTrim": false
  },
  "frame": {
    "_class": "rect",
    "constrainProportions": false,
    "do_objectID": "041FD56D-85DD-4D49-802E-FF01075C0BF8",
    "height": 24,
    "width": 82,
    "x": 42,
    "y": 32
  },
  "glyphBounds": "{{0, 6}, {82, 15}}",
  "hasClippingMask": false,
  "isFixedToViewport": false,
  "isFlippedHorizontal": false,
  "isFlippedVertical": false,
  "isLocked": false,
  "isVisible": true,
  "layerListExpandedType": 0,
  "lineSpacingBehaviour": 2,
  "name": "Wrong input:",
  "nameIsFixed": true,
  "originalObjectID": "C19756ED-042E-444D-8192-8A4FE3824F63",
  "resizingConstraint": 11,
  "resizingType": 0,
  "rotation": 0,
  "sharedStyleID": "F365B86F-A612-45DC-8D44-02C28BBE7BC5",
  "shouldBreakMaskChain": false,
  "style": {
    "_class": "style",
    "do_objectID": "1858A818-336F-4019-9A8C-46DCC7FB2903",
    "endMarkerType": 0,
    "miterLimit": 10,
    "startMarkerType": 0,
    "textStyle": {
      "_class": "textStyle",
      "do_objectID": "CC865910-95C6-47FB-A932-DCAD3A3C99E0",
      "encodedAttributes": {
        "MSAttributedStringColorAttribute": {
          "_class": "color",
          "alpha": 1,
          "blue": 0.2941176470588236,
          "green": 0.2941176470588236,
          "red": 1
        },
        "MSAttributedStringFontAttribute": {
          "_class": "fontDescriptor",
          "attributes": {
            "name": "OpenSans",
            "size": 14
          }
        },
        "kerning": 0,
        "paragraphStyle": {
          "_class": "paragraphStyle",
          "alignment": 0,
          "baseWritingDirection": 0,
          "headerLevel": 1,
          "maximumLineHeight": 24,
          "minimumLineHeight": 24
        }
      },
      "verticalAlignment": 0
    },
    "windingRule": 1
  },
  "textBehaviour": 0
}