{
  "_class": "group",
  "booleanOperation": 0,
  "clippingMaskMode": 0,
  "do_objectID": "717B62BE-7A5B-4F88-90FC-9F542CD32F75",
  "exportOptions": {
    "_class": "exportOptions",
    "exportFormats": [
    ],
    "includedLayerIds": [
    ],
    "layerOptions": 0,
    "shouldTrim": false
  },
  "frame": {
    "_class": "rect",
    "constrainProportions": false,
    "height": 40,
    "width": 40,
    "x": 0,
    "y": 0
  },
  "hasClickThrough": false,
  "hasClippingMask": false,
  "isFixedToViewport": false,
  "isFlippedHorizontal": false,
  "isFlippedVertical": false,
  "isLocked": false,
  "isVisible": true,
  "layerListExpandedType": 2,
  "layers": [
    {
      "class": "rectangle",
      "id": "41C537D8-ADD8-4CFA-91B1-D074BD8770C5"
    },
    {
      "class": "rectangle",
      "id": "D545F6BD-D5BD-49BA-8274-598593CE0148"
    },
    {
      "class": "symbolInstance",
      "id": "EDDF5963-4EDB-4166-8CE5-F56DE0EE829C"
    }
  ],
  "name": "Disabled",
  "nameIsFixed": true,
  "originalObjectID": "717B62BE-7A5B-4F88-90FC-9F542CD32F75",
  "resizingConstraint": 63,
  "resizingType": 0,
  "rotation": 0,
  "sharedStyleID": "310B732D-4026-4CC7-8BFF-13003C6AF47A",
  "shouldBreakMaskChain": false,
  "style": {
    "_class": "style",
    "contextSettings": {
      "_class": "graphicsContextSettings",
      "blendMode": 0,
      "opacity": 0.4000000059604645
    },
    "do_objectID": "F0EBFE66-501E-4B9C-8FCB-01D1E7712CFF",
    "endMarkerType": 0,
    "miterLimit": 10,
    "startMarkerType": 0,
    "windingRule": 1
  }
}