{
  "_class": "symbolInstance",
  "booleanOperation": 0,
  "clippingMaskMode": 0,
  "do_objectID": "ACE265D5-CB61-408D-839E-EF93C06600EC",
  "exportOptions": {
    "_class": "exportOptions",
    "do_objectID": "130D1DE6-A471-456C-9E39-6FCB0F185DBE",
    "exportFormats": [
      {
        "_class": "exportFormat",
        "absoluteSize": 0,
        "fileFormat": "svg",
        "name": "",
        "namingScheme": 0,
        "scale": 1,
        "visibleScaleType": 0
      }
    ],
    "includedLayerIds": [
    ],
    "layerOptions": 0,
    "shouldTrim": false
  },
  "frame": {
    "_class": "rect",
    "constrainProportions": false,
    "do_objectID": "73D93FD8-5BC2-4145-A08F-80CF69289D07",
    "height": 24,
    "width": 24,
    "x": 72,
    "y": 8
  },
  "hasClippingMask": false,
  "horizontalSpacing": 0,
  "isFixedToViewport": false,
  "isFlippedHorizontal": false,
  "isFlippedVertical": false,
  "isLocked": false,
  "isVisible": true,
  "layerListExpandedType": 0,
  "name": "Right:",
  "nameIsFixed": true,
  "originalObjectID": "B37C5785-7F8C-40FB-95CA-8D9AD1EF8FF3",
  "overrideValues": [
    {
      "_class": "overrideValue",
      "do_objectID": "743EE275-8F34-46B5-A524-3D079E5D5508",
      "overrideName": "15B2F121-AEEB-4354-8582-3773BB693A34_symbolID",
      "value": "DAF2E124-158A-49A0-B1A5-CECD824369A0"
    }
  ],
  "resizingConstraint": 44,
  "resizingType": 0,
  "rotation": 0,
  "scale": 1,
  "shouldBreakMaskChain": false,
  "style": {
    "_class": "style",
    "do_objectID": "5023009F-4888-457D-BF5A-2E78B321713B",
    "endMarkerType": 0,
    "miterLimit": 10,
    "startMarkerType": 0,
    "windingRule": 1
  },
  "symbolID": "43542772-BDFC-4556-9158-4F7843066E67",
  "verticalSpacing": 0
}