{
  "_class": "symbolInstance",
  "booleanOperation": 0,
  "clippingMaskMode": 0,
  "do_objectID": "09DC482C-A77C-4E9E-AD24-7CDA9374F24F",
  "exportOptions": {
    "_class": "exportOptions",
    "do_objectID": "B7C320D3-C39F-4C94-A476-C00ECFC12355",
    "exportFormats": [
    ],
    "includedLayerIds": [
    ],
    "layerOptions": 0,
    "shouldTrim": false
  },
  "frame": {
    "_class": "rect",
    "constrainProportions": true,
    "do_objectID": "CF059517-2195-4F59-9739-F452ECA683F5",
    "height": 160,
    "width": 160,
    "x": 0,
    "y": 34
  },
  "hasClippingMask": false,
  "horizontalSpacing": 0,
  "isFixedToViewport": false,
  "isFlippedHorizontal": false,
  "isFlippedVertical": false,
  "isLocked": false,
  "isVisible": true,
  "layerListExpandedType": 0,
  "name": "0: Icons / Dark / Bell",
  "nameIsFixed": false,
  "originalObjectID": "F6A05939-C065-4F7B-BC38-18805B1009C9",
  "overrideValues": [
  ],
  "resizingConstraint": 63,
  "resizingType": 0,
  "rotation": 0,
  "scale": 3.333333333333333,
  "shouldBreakMaskChain": false,
  "style": {
    "_class": "style",
    "blur": {
      "_class": "blur",
      "center": "{0.5, 0.5}",
      "do_objectID": "F3749177-86D6-4165-BE65-54DC645C5C43",
      "isEnabled": false,
      "motionAngle": 0,
      "radius": 33.33333333333334,
      "saturation": 1,
      "type": 0
    },
    "do_objectID": "C5713246-E5F7-49D6-B9F0-486A871A7302",
    "endMarkerType": 0,
    "miterLimit": 10,
    "startMarkerType": 0,
    "windingRule": 1
  },
  "symbolID": "7A8D2B8B-0F04-423B-A35E-8F79458DF714",
  "verticalSpacing": 0
}