{
  "_class": "symbolInstance",
  "booleanOperation": 0,
  "clippingMaskMode": 0,
  "do_objectID": "3B1E60ED-879D-4F15-885C-E04729289284",
  "exportOptions": {
    "_class": "exportOptions",
    "do_objectID": "05911290-A57C-44F3-9791-833A3CC3CEA4",
    "exportFormats": [
    ],
    "includedLayerIds": [
    ],
    "layerOptions": 0,
    "shouldTrim": false
  },
  "frame": {
    "_class": "rect",
    "constrainProportions": false,
    "do_objectID": "F1C6A16C-4ECB-4B85-AA83-50B10AA581EA",
    "height": 40,
    "width": 40,
    "x": 258,
    "y": 392
  },
  "hasClippingMask": false,
  "horizontalSpacing": 0,
  "isFixedToViewport": false,
  "isFlippedHorizontal": false,
  "isFlippedVertical": false,
  "isLocked": false,
  "isVisible": true,
  "layerListExpandedType": 0,
  "name": "1: Atoms / Buttons / Primary / Text / Hover Copy 3",
  "nameIsFixed": true,
  "originalObjectID": "FD6E4CF6-9E3C-4FA7-8A69-DDB2C3BD8378",
  "overrideValues": [
  ],
  "resizingConstraint": 63,
  "resizingType": 0,
  "rotation": 0,
  "scale": 1,
  "shouldBreakMaskChain": false,
  "style": {
    "_class": "style",
    "do_objectID": "F493D9BA-C48F-4071-98C0-A73E6B451E0E",
    "endMarkerType": 0,
    "miterLimit": 10,
    "startMarkerType": 0,
    "windingRule": 1
  },
  "symbolID": "6A63602C-E847-4C80-8ED3-7ED0B4E05556",
  "verticalSpacing": 0
}