{
  "_class": "text",
  "attributedString": {
    "_class": "attributedString",
    "attributes": [
      {
        "_class": "stringAttribute",
        "attributes": {
          "MSAttributedStringColorAttribute": {
            "_class": "color",
            "alpha": 1,
            "blue": 0.1333333333333333,
            "green": 0.1333333333333333,
            "red": 0.1333333333333333
          },
          "MSAttributedStringFontAttribute": {
            "_class": "fontDescriptor",
            "attributes": {
              "name": "OpenSans",
              "size": 14
            }
          },
          "kerning": 0,
          "paragraphStyle": {
            "_class": "paragraphStyle",
            "alignment": 0,
            "baseWritingDirection": 0,
            "headerLevel": 1,
            "maximumLineHeight": 24,
            "minimumLineHeight": 24
          }
        },
        "length": 10,
        "location": 0
      }
    ],
    "string": "Unselected"
  },
  "automaticallyDrawOnUnderlyingPath": false,
  "booleanOperation": 0,
  "clippingMaskMode": 0,
  "do_objectID": "0FAC3F95-688C-438D-B8DD-E4C041CF55AE",
  "dontSynchroniseWithSymbol": true,
  "exportOptions": {
    "_class": "exportOptions",
    "do_objectID": "E1B38906-B943-48B7-81EC-3F50251EDC7B",
    "exportFormats": [
    ],
    "includedLayerIds": [
    ],
    "layerOptions": 0,
    "shouldTrim": false
  },
  "frame": {
    "_class": "rect",
    "constrainProportions": false,
    "do_objectID": "4E43651B-6C0B-459A-B33E-1F5E40F80258",
    "height": 24,
    "width": 73,
    "x": 32,
    "y": 0.2222222222221717
  },
  "glyphBounds": "{{1, 6}, {71, 12}}",
  "hasClippingMask": false,
  "isFixedToViewport": false,
  "isFlippedHorizontal": false,
  "isFlippedVertical": false,
  "isLocked": false,
  "isVisible": true,
  "layerListExpandedType": 0,
  "lineSpacingBehaviour": 2,
  "name": "Wording:",
  "nameIsFixed": true,
  "originalObjectID": "42094BC2-C3D6-484E-9FEF-9A05165758AD",
  "resizingConstraint": 2,
  "resizingType": 0,
  "rotation": 0,
  "sharedStyleID": "ED3D21F0-05D7-49DE-9ECB-A5A3A7A14007",
  "shouldBreakMaskChain": false,
  "style": {
    "_class": "style",
    "do_objectID": "C6C5F50D-7791-410C-B368-E8BCA4A480CD",
    "endMarkerType": 0,
    "miterLimit": 10,
    "startMarkerType": 0,
    "textStyle": {
      "_class": "textStyle",
      "do_objectID": "26234FB8-8B2B-4933-97A3-63D8870BB043",
      "encodedAttributes": {
        "MSAttributedStringColorAttribute": {
          "_class": "color",
          "alpha": 1,
          "blue": 0.1333333333333333,
          "green": 0.1333333333333333,
          "red": 0.1333333333333333
        },
        "MSAttributedStringFontAttribute": {
          "_class": "fontDescriptor",
          "attributes": {
            "name": "OpenSans",
            "size": 14
          }
        },
        "kerning": 0,
        "paragraphStyle": {
          "_class": "paragraphStyle",
          "alignment": 0,
          "baseWritingDirection": 0,
          "headerLevel": 1,
          "maximumLineHeight": 24,
          "minimumLineHeight": 24
        }
      },
      "verticalAlignment": 0
    },
    "windingRule": 1
  },
  "textBehaviour": 0
}