{
  "_class": "shapePath",
  "booleanOperation": -1,
  "clippingMaskMode": 0,
  "do_objectID": "58199C32-3290-4610-B1AA-A4697FCD8E3E",
  "edited": true,
  "exportOptions": {
    "_class": "exportOptions",
    "do_objectID": "8570DBC5-3EA1-4589-9598-ACD0765E3CA2",
    "exportFormats": [
    ],
    "includedLayerIds": [
    ],
    "layerOptions": 0,
    "shouldTrim": false
  },
  "frame": {
    "_class": "rect",
    "constrainProportions": false,
    "do_objectID": "83048C0C-B7B7-475D-ADBF-CCF6A4C43478",
    "height": 19,
    "width": 2,
    "x": 42,
    "y": 11
  },
  "hasClippingMask": false,
  "isClosed": false,
  "isFixedToViewport": false,
  "isFlippedHorizontal": false,
  "isFlippedVertical": false,
  "isLocked": false,
  "isVisible": true,
  "layerListExpandedType": 0,
  "name": "Line",
  "nameIsFixed": false,
  "pointRadiusBehaviour": 1,
  "points": [
    {
      "_class": "curvePoint",
      "cornerRadius": 0,
      "curveFrom": "{0.62499999999999989, 0.052631578947368397}",
      "curveMode": 1,
      "curveTo": "{0.62499999999999989, 0.052631578947368397}",
      "hasCurveFrom": false,
      "hasCurveTo": false,
      "point": "{0.5, 0}"
    },
    {
      "_class": "curvePoint",
      "cornerRadius": 0,
      "curveFrom": "{0.75, -0.15789473684210523}",
      "curveMode": 1,
      "curveTo": "{0.75, -0.15789473684210523}",
      "hasCurveFrom": false,
      "hasCurveTo": false,
      "point": "{0.5, 0.99999999999999989}"
    }
  ],
  "resizingConstraint": 41,
  "resizingType": 0,
  "rotation": 0,
  "shouldBreakMaskChain": false,
  "style": {
    "_class": "style",
    "borders": [
      {
        "_class": "border",
        "color": {
          "_class": "color",
          "alpha": 1,
          "blue": 0.6823529411764706,
          "green": 0.235294117647059,
          "red": 0.03137254901960781
        },
        "fillType": 0,
        "isEnabled": true,
        "position": 0,
        "thickness": 1
      }
    ],
    "do_objectID": "B9BE2FEC-125E-40C7-B9C8-8413791F1202",
    "endMarkerType": 0,
    "fills": [
      {
        "_class": "fill",
        "color": {
          "_class": "color",
          "alpha": 1,
          "blue": 0.847,
          "green": 0.847,
          "red": 0.847
        },
        "fillType": 0,
        "isEnabled": false,
        "noiseIndex": 0,
        "noiseIntensity": 0,
        "patternFillType": 1,
        "patternTileScale": 1
      }
    ],
    "miterLimit": 10,
    "startMarkerType": 0,
    "windingRule": 1
  }
}