{
  "_class": "rectangle",
  "booleanOperation": -1,
  "clippingMaskMode": 0,
  "do_objectID": "2C9D262A-CD25-494D-BF8D-F673622FAC4D",
  "edited": true,
  "exportOptions": {
    "_class": "exportOptions",
    "do_objectID": "B667A4F1-CF29-4667-AAAC-E3B5706B7076",
    "exportFormats": [
    ],
    "includedLayerIds": [
    ],
    "layerOptions": 0,
    "shouldTrim": false
  },
  "fixedRadius": 4,
  "frame": {
    "_class": "rect",
    "constrainProportions": false,
    "do_objectID": "816D84DC-B84D-4CB0-8C47-61931AB3FF2A",
    "height": 40,
    "width": 40,
    "x": 0,
    "y": 0
  },
  "hasClippingMask": false,
  "hasConvertedToNewRoundCorners": true,
  "isClosed": true,
  "isFixedToViewport": false,
  "isFlippedHorizontal": false,
  "isFlippedVertical": false,
  "isLocked": false,
  "isVisible": true,
  "layerListExpandedType": 0,
  "name": "Rectangle 28 Copy 2",
  "nameIsFixed": false,
  "originalObjectID": "6E01974A-382E-4F91-8DD3-3013A00BDF57",
  "pointRadiusBehaviour": 0,
  "points": [
    {
      "_class": "curvePoint",
      "cornerRadius": 4,
      "curveFrom": "{0, 0}",
      "curveMode": 1,
      "curveTo": "{0, 0}",
      "hasCurveFrom": false,
      "hasCurveTo": false,
      "point": "{0, 0}"
    },
    {
      "_class": "curvePoint",
      "cornerRadius": 4,
      "curveFrom": "{0.99999999999999889, 0}",
      "curveMode": 1,
      "curveTo": "{0.99999999999999889, 0}",
      "hasCurveFrom": false,
      "hasCurveTo": false,
      "point": "{0.99999999999999889, 0}"
    },
    {
      "_class": "curvePoint",
      "cornerRadius": 4,
      "curveFrom": "{0.99999999999999889, 1}",
      "curveMode": 1,
      "curveTo": "{0.99999999999999889, 1}",
      "hasCurveFrom": false,
      "hasCurveTo": false,
      "point": "{0.99999999999999889, 1}"
    },
    {
      "_class": "curvePoint",
      "cornerRadius": 4,
      "curveFrom": "{0, 1}",
      "curveMode": 1,
      "curveTo": "{0, 1}",
      "hasCurveFrom": false,
      "hasCurveTo": false,
      "point": "{0, 1}"
    }
  ],
  "resizingConstraint": 63,
  "resizingType": 0,
  "rotation": 0,
  "sharedStyleID": "B57D3081-7E60-4250-A9F4-3A2D91B2B8AB",
  "shouldBreakMaskChain": false,
  "style": {
    "_class": "style",
    "borders": [
      {
        "_class": "border",
        "color": {
          "_class": "color",
          "alpha": 1,
          "blue": 0.8666666666666667,
          "green": 0.8666666666666667,
          "red": 0.8666666666666667
        },
        "fillType": 0,
        "isEnabled": true,
        "position": 1,
        "thickness": 1
      }
    ],
    "contextSettings": {
      "_class": "graphicsContextSettings",
      "blendMode": 0,
      "do_objectID": "76F9D0C9-80B9-46CB-8CDE-100B40CF1E90",
      "opacity": 0.6000000238418579
    },
    "do_objectID": "76BC7D2A-0945-4011-BB24-88ABC28034AE",
    "endMarkerType": 0,
    "miterLimit": 10,
    "startMarkerType": 0,
    "windingRule": 1
  }
}