{
  "_class": "text",
  "attributedString": {
    "_class": "attributedString",
    "attributes": [
      {
        "_class": "stringAttribute",
        "attributes": {
          "MSAttributedStringColorAttribute": {
            "_class": "color",
            "alpha": 1,
            "blue": 0.1333333333333333,
            "green": 0.1333333333333333,
            "red": 0.1333333333333333
          },
          "MSAttributedStringFontAttribute": {
            "_class": "fontDescriptor",
            "attributes": {
              "name": "OpenSans",
              "size": 36
            }
          },
          "kerning": 0,
          "paragraphStyle": {
            "_class": "paragraphStyle",
            "alignment": 0,
            "baseWritingDirection": 0,
            "headerLevel": 1,
            "maximumLineHeight": 48,
            "minimumLineHeight": 48
          }
        },
        "length": 11,
        "location": 0
      }
    ],
    "string": "Column grid"
  },
  "automaticallyDrawOnUnderlyingPath": false,
  "booleanOperation": 0,
  "clippingMaskMode": 0,
  "do_objectID": "BE6DDD32-05AC-4787-B298-040BE332B496",
  "dontSynchroniseWithSymbol": false,
  "exportOptions": {
    "_class": "exportOptions",
    "do_objectID": "83BD7641-4462-4EEB-AFE6-EBF8F9E93383",
    "exportFormats": [
    ],
    "includedLayerIds": [
    ],
    "layerOptions": 0,
    "shouldTrim": false
  },
  "frame": {
    "_class": "rect",
    "constrainProportions": false,
    "do_objectID": "A7F60E42-0A02-4ED5-9B50-F09979D57F4F",
    "height": 48,
    "width": 285,
    "x": 41,
    "y": 48
  },
  "glyphBounds": "{{2, 10}, {202, 37}}",
  "hasClippingMask": false,
  "isFixedToViewport": false,
  "isFlippedHorizontal": false,
  "isFlippedVertical": false,
  "isLocked": false,
  "isVisible": true,
  "layerListExpandedType": 0,
  "lineSpacingBehaviour": 2,
  "name": "Column grid",
  "nameIsFixed": false,
  "resizingConstraint": 47,
  "resizingType": 0,
  "rotation": 0,
  "sharedStyleID": "B5BE697A-59AD-4C68-A20C-58A308D3DA0A",
  "shouldBreakMaskChain": false,
  "style": {
    "_class": "style",
    "do_objectID": "FB6C5A46-C09A-4C2C-B7F6-99745FA7411E",
    "endMarkerType": 0,
    "miterLimit": 10,
    "startMarkerType": 0,
    "textStyle": {
      "_class": "textStyle",
      "do_objectID": "93A448EA-B1D1-4FAE-A9E0-684A8E3223A5",
      "encodedAttributes": {
        "MSAttributedStringColorAttribute": {
          "_class": "color",
          "alpha": 1,
          "blue": 0.1333333333333333,
          "green": 0.1333333333333333,
          "red": 0.1333333333333333
        },
        "MSAttributedStringFontAttribute": {
          "_class": "fontDescriptor",
          "attributes": {
            "name": "OpenSans",
            "size": 36
          }
        },
        "kerning": 0,
        "paragraphStyle": {
          "_class": "paragraphStyle",
          "alignment": 0,
          "baseWritingDirection": 0,
          "headerLevel": 1,
          "maximumLineHeight": 48,
          "minimumLineHeight": 48
        }
      },
      "verticalAlignment": 0
    },
    "windingRule": 1
  },
  "textBehaviour": 1
}